{
  "config": {
    "feature": {
      "config": {
        "feature": {
          "config": {
            "feature": {
              "config": {
                "targets": [
                  {
                    "target": {
                      "block": "minecraft:sand",
                      "predicate_type": "minecraft:block_match"
                    },
                    "state": {
                      "Name": "minecraft:clay"
                    }
                  }
                ],
                "size": 33,
                "discard_chance_on_air_exposure": 0.0
              },
              "type": "modern_beta:ore_clay"
            },
            "decorator": {
              "config": {
                "bottom_inclusive": {
                  "absolute": 0
                },
                "top_inclusive": {
                  "absolute": 128
                }
              },
              "type": "minecraft:range"
            }
          },
          "type": "minecraft:decorated"
        },
        "decorator": {
          "config": {},
          "type": "minecraft:square"
        }
      },
      "type": "minecraft:decorated"
    },
    "decorator": {
      "config": {
        "count": 1
      },
      "type": "minecraft:count"
    }
  },
  "type": "minecraft:decorated"
}